<powerpagecomponent powerpagecomponentid="7eff40b3-2c73-4aa5-9369-579b587d991b">
  <content>{"display_name":"Search/Title","type":756150000,"value":"&lt;span&gt;Search&lt;/span&gt;"}</content>
  <iscustomizable>1</iscustomizable>
  <name>Search/Title</name>
  <powerpagecomponenttype>7</powerpagecomponenttype>
  <powerpagesiteid>
    <powerpagesiteid>8a06a503-9ac7-4255-a18f-4522d3048b16</powerpagesiteid>
  </powerpagesiteid>
  <powerpagesitelanguageid>
    <powerpagesitelanguageid>75833fe0-0eb4-4fa4-98db-b96a7ac5b501</powerpagesitelanguageid>
  </powerpagesitelanguageid>
  <statecode>0</statecode>
  <statuscode>1</statuscode>
</powerpagecomponent>